s3_pypi_publisher/__init__.py
s3_pypi_publisher/publish_package.py
s3_pypi_publisher-0.1.1.data/scripts/publish_package
s3_pypi_publisher-0.1.1.dist-info/LICENSE
s3_pypi_publisher-0.1.1.dist-info/METADATA
s3_pypi_publisher-0.1.1.dist-info/WHEEL
s3_pypi_publisher-0.1.1.dist-info/top_level.txt
s3_pypi_publisher-0.1.1.dist-info/RECORD
