Metadata-Version: 2.1
Name: s3-pypi-publisher
Version: 0.1.1
Summary: A utility to publish Python packages to S3 buckets
Home-page: https://github.com/gzzo/s3_pypi_publisher
Author: Guido Rainuzzo
Author-email: hi@guido.nyc
License: License :: OSI Approved :: Apache Software License 2.0 (Apache-2.0)
Platform: UNKNOWN
Requires-Dist: boto3
Requires-Dist: jinja2
